LICENSE
README.md
setup.py
varc.py
tests/__init__.py
tests/test_import.py
tests/test_shared.py
tests/test_linux/__init__.py
tests/test_linux/test_base.py
varc.egg-info/PKG-INFO
varc.egg-info/SOURCES.txt
varc.egg-info/dependency_links.txt
varc.egg-info/requires.txt
varc.egg-info/top_level.txt
varc_core/__init__.py
varc_core/exceptions.py
varc_core/systems/__init__.py
varc_core/systems/base_system.py
varc_core/systems/linux.py
varc_core/systems/osx.py
varc_core/systems/windows.py
varc_core/utils/__init__.py
varc_core/utils/dumpfile_extraction.py
varc_core/utils/string_manips.py
varc_core/utils/yara_test_target.py