Metadata-Version: 2.1
Name: varc
Version: 1.0.9
Summary: varc Volatile Artifact Collector
Home-page: https://github.com/cado-security/varc
Download-URL: https://github.com/cado-security/varc/archive/refs/heads/main.zip
Author: Cado Security
Author-email: varc@cadosecurity.com
License-File: LICENSE
Requires-Dist: psutil
Requires-Dist: mss
Requires-Dist: tqdm
Requires-Dist: pymem
Requires-Dist: yara-python
